swiftllm/__init__.py
swiftllm/genai_wrapper.py
swiftllm/groq_wrapper.py
swiftllm/openai_wrapper.py
SwiftLLM-0.0.6.dist-info/LICENSE
SwiftLLM-0.0.6.dist-info/METADATA
SwiftLLM-0.0.6.dist-info/WHEEL
SwiftLLM-0.0.6.dist-info/top_level.txt
SwiftLLM-0.0.6.dist-info/RECORD
